{"K":[[557,0,256.5],[0,557,256.5],[0,0,1]],"R":[[1,0,0],[0,-0.8678522,0.4968225],[0,-0.4968225,-0.8678522]],"t":[-1.48,0.08187342,9.43787],"minDepth":7.431988,"maxDepth":11.49697,"objects":[{"id":0,"shape":"sphere","size":0.2,"material":"smooth_pink_sphere","position":[-0.7503494,0.45,0.8004522],"screenPosition":[130.6283,216.2953]},{"id":1,"shape":"sphere","size":0.2,"material":"matt_orange_sphere","position":[-2.25035,0.45,0.8004522],"screenPosition":[46.31081,216.2953]},{"id":2,"shape":"sphere","size":0.2,"material":"matt_orange_sphere","position":[-1.500349,0.45,2.100452],"screenPosition":[105.5943,187.7596]},{"id":3,"shape":"sphere","size":0.2,"material":"matt_orange_sphere","position":[-0.8496681,0.45,-1.418713],"screenPosition":[93.45279,283.6432]},{"id":4,"shape":"cube","size":0.2828427,"material":"smooth_blue_cube","position":[3.194104,0.45,-1.973104],"screenPosition":[383.2679,305.8663]}]}