{"K":[[557,0,256.5],[0,557,256.5],[0,0,1]],"R":[[1,0,0],[0,-0.8678522,0.4968225],[0,-0.4968225,-0.8678522]],"t":[-1.48,0.08187342,9.43787],"minDepth":6.820818,"maxDepth":10.82072,"objects":[{"id":0,"shape":"sphere","size":0.2,"material":"matt_orange_sphere","position":[1.213301,0.45,-0.5350584],"screenPosition":[239.0226,253.2735]},{"id":1,"shape":"sphere","size":0.2,"material":"smooth_pink_sphere","position":[-0.2866992,0.45,-0.5350584],"screenPosition":[143.5363,253.2735]},{"id":2,"shape":"sphere","size":0.2,"material":"matt_orange_sphere","position":[0.4633008,0.45,0.7649416],"screenPosition":[198.6713,217.1662]},{"id":3,"shape":"cube","size":0.2828427,"material":"smooth_green_cube","position":[0.7818652,0.45,-2.500969],"screenPosition":[200.7941,329.8476]},{"id":4,"shape":"cube","size":0.2828427,"material":"smooth_green_cube","position":[0.8842968,0.45,1.605959],"screenPosition":[224.7212,197.8987]}]}