{"K":[[557,0,256.5],[0,557,256.5],[0,0,1]],"R":[[0.9993284,0,-0.03664367],[0.01305426,-0.9343911,0.3560095],[-0.03423952,-0.3562488,-0.9337636]],"t":[-1.449744,-0.08999181,9.639576],"minDepth":6.196747,"maxDepth":9.367163,"objects":[{"id":0,"shape":"sphere","size":0.25,"material":"matt_green_sphere","position":[0.4560712,0.5,-1.118452],"screenPosition":[187.3841,245.8528]},{"id":1,"shape":"sphere","size":0.25,"material":"smooth_blue_sphere","position":[-0.2439288,0.5,-1.118452],"screenPosition":[141.3338,245.2776]},{"id":2,"shape":"sphere","size":0.35,"material":"smooth_blue_sphere","position":[2.325191,0.6,-0.02600634],"screenPosition":[308.1591,219.4909]},{"id":3,"shape":"sphere","size":0.35,"material":"matt_green_sphere","position":[3.001747,0.6,-2.049432],"screenPosition":[366.8749,264.8839]},{"id":4,"shape":"cube","size":0.3535534,"material":"matt_red_cube","position":[2.147261,0.5,-3.052363],"screenPosition":[305.7746,303.4988]}]}