{"K":[[557,0,256.5],[0,557,256.5],[0,0,1]],"R":[[0.9993284,0,-0.03664367],[0.01305426,-0.9343911,0.3560095],[-0.03423952,-0.3562488,-0.9337636]],"t":[-1.449744,-0.08999181,9.639576],"minDepth":7.334166,"maxDepth":11.57585,"objects":[{"id":0,"shape":"sphere","size":0.25,"material":"matt_green_sphere","position":[0.611472,0.5,1.016368],"screenPosition":[213.0336,207.1577]},{"id":1,"shape":"sphere","size":0.25,"material":"smooth_blue_sphere","position":[2.786122,0.5,2.205764],"screenPosition":[324.997,192.3286]},{"id":2,"shape":"cube","size":0.2474874,"material":"matt_blue_cube","position":[-1.027665,0.425,-2.594408],"screenPosition":[54.26404,289.1896]},{"id":3,"shape":"sphere","size":0.0875,"material":"smooth_red_sphere","position":[4.295016,0.3375,1.833042],"screenPosition":[402.214,205.6535]},{"id":4,"shape":"cube","size":0.3535534,"material":"smooth_blue_cube","position":[3.71537,0.5,-1.216698],"screenPosition":[406.7332,250.8683]}]}