{"K":[[557,0,256.5],[0,557,256.5],[0,0,1]],"R":[[0.9993284,0,-0.03664367],[0.01305426,-0.9343911,0.3560095],[-0.03423952,-0.3562488,-0.9337636]],"t":[-1.449744,-0.08999181,9.639576],"minDepth":8.24099,"maxDepth":11.80705,"objects":[{"id":0,"shape":"sphere","size":0.25,"material":"smooth_blue_sphere","position":[-0.9052849,0.5,2.186043],"screenPosition":[146.1658,190.9365]},{"id":1,"shape":"cube","size":0.3535534,"material":"matt_red_cube","position":[3.607592,0.5,2.092072],"screenPosition":[366.1075,194.0969]},{"id":2,"shape":"cube","size":0.4949747,"material":"smooth_green_cube","position":[3.240452,0.6,-0.841921],"screenPosition":[370.7919,235.8462]},{"id":3,"shape":"sphere","size":0.35,"material":"matt_green_sphere","position":[1.264204,0.6,0.1169606],"screenPosition":[245.3137,216.3446]},{"id":4,"shape":"cube","size":0.3535534,"material":"smooth_green_cube","position":[-0.2486767,0.5,1.587219],"screenPosition":[172.5881,198.7593]}]}