{"K":[[557,0,256.5],[0,557,256.5],[0,0,1]],"R":[[1,0,0],[0,-0.8678522,0.4968225],[0,-0.4968225,-0.8678522]],"t":[-1.48,0.08187342,9.43787],"minDepth":6.543144,"maxDepth":9.295598,"objects":[{"id":0,"shape":"cube","size":0.35,"material":"smooth_green_cube","position":[0.7125922,0.4974874,-2.771566],"screenPosition":[193.005,340.313]},{"id":1,"shape":"sphere","size":0.1,"material":"matt_orange_sphere","position":[2.66033,0.35,-3.105907],"screenPosition":[356.0902,368.0366]},{"id":2,"shape":"sphere","size":0.175,"material":"smooth_pink_sphere","position":[-0.172612,0.425,-3.002298],"screenPosition":[116.9755,357.3398]},{"id":3,"shape":"sphere","size":0.35,"material":"smooth_pink_sphere","position":[2.071207,0.6,-0.08111393],"screenPosition":[292.3092,231.5236]},{"id":4,"shape":"cube","size":0.4949747,"material":"matt_pink_cube","position":[-0.3602561,0.6,-0.2877156],"screenPosition":[140.7004,237.461]}]}